dnv/__init__.py
dnv/net/__init__.py
dnv/net/runtime/__init__.py
dnv/net/runtime/context_manager_utils.py
dnv/net/runtime/runtime.py
dnv/net/runtime/runtimeconfig.json
dnv/net/runtime/.net/LICENSE.txt
dnv/net/runtime/.net/ThirdPartyNotices.txt
dnv/net/runtime/.net/dotnet
dnv/net/runtime/.net/host/fxr/8.0.4/libhostfxr.so
dnv/net/runtime/.net/shared/Microsoft.NETCore.App/8.0.4/.version
dnv/net/runtime/.net/shared/Microsoft.NETCore.App/8.0.4/Microsoft.CSharp.dll
dnv/net/runtime/.net/shared/Microsoft.NETCore.App/8.0.4/Microsoft.NETCore.App.deps.json
dnv/net/runtime/.net/shared/Microsoft.NETCore.App/8.0.4/Microsoft.NETCore.App.runtimeconfig.json
dnv/net/runtime/.net/shared/Microsoft.NETCore.App/8.0.4/Microsoft.VisualBasic.Core.dll
dnv/net/runtime/.net/shared/Microsoft.NETCore.App/8.0.4/Microsoft.VisualBasic.dll
dnv/net/runtime/.net/shared/Microsoft.NETCore.App/8.0.4/Microsoft.Win32.Primitives.dll
dnv/net/runtime/.net/shared/Microsoft.NETCore.App/8.0.4/Microsoft.Win32.Registry.dll
dnv/net/runtime/.net/shared/Microsoft.NETCore.App/8.0.4/System.AppContext.dll
dnv/net/runtime/.net/shared/Microsoft.NETCore.App/8.0.4/System.Buffers.dll
dnv/net/runtime/.net/shared/Microsoft.NETCore.App/8.0.4/System.Collections.Concurrent.dll
dnv/net/runtime/.net/shared/Microsoft.NETCore.App/8.0.4/System.Collections.Immutable.dll
dnv/net/runtime/.net/shared/Microsoft.NETCore.App/8.0.4/System.Collections.NonGeneric.dll
dnv/net/runtime/.net/shared/Microsoft.NETCore.App/8.0.4/System.Collections.Specialized.dll
dnv/net/runtime/.net/shared/Microsoft.NETCore.App/8.0.4/System.Collections.dll
dnv/net/runtime/.net/shared/Microsoft.NETCore.App/8.0.4/System.ComponentModel.Annotations.dll
dnv/net/runtime/.net/shared/Microsoft.NETCore.App/8.0.4/System.ComponentModel.DataAnnotations.dll
dnv/net/runtime/.net/shared/Microsoft.NETCore.App/8.0.4/System.ComponentModel.EventBasedAsync.dll
dnv/net/runtime/.net/shared/Microsoft.NETCore.App/8.0.4/System.ComponentModel.Primitives.dll
dnv_net_runtime-1.0.0.dist-info/LICENSE
dnv_net_runtime-1.0.0.dist-info/METADATA
dnv_net_runtime-1.0.0.dist-info/WHEEL
dnv_net_runtime-1.0.0.dist-info/top_level.txt
dnv_net_runtime-1.0.0.dist-info/RECORD
