Metadata-Version: 2.1
Name: dnv-net-runtime
Version: 1.0.0
Summary: This package contains the .NET Runtime for console-based applications, allowing seamless integration with the .NET Common Language Runtime (CLR) by leveraging the Python.NET package.
Author-email: DNV <onecompute@dnv.com>
License: MIT License
Keywords: dotnet,dotnetruntime,netruntime,net.runtime
Classifier: License :: OSI Approved :: MIT License
Requires-Python: >=3.10
License-File: LICENSE
Requires-Dist: pythonnet ==3.0.3
